asgardeo_ai/__init__.py
asgardeo_ai/agent_auth_manager.py
asgardeo_ai-0.2.2.dist-info/METADATA
asgardeo_ai-0.2.2.dist-info/WHEEL
asgardeo_ai-0.2.2.dist-info/RECORD
